hibee
