Metadata-Version: 2.1
Name: Hibee
Version: 5.0.dev20230404184216
Summary: A stinking framework developed in Pyhon for masterbees not newbees.
Home-page: https://www.hibeeproject.com/
Author: JABA Applets Foundation
Author-email: info@jabaapplets.com
License: BSD-3-Clause
Project-URL: Documentation, https://docs.hibeeproject.com/
Project-URL: Release notes, https://docs.hibeeproject.com/en/stable/releases/
Project-URL: Funding, https://www.jabaapplets.com/fundraising/
Project-URL: Source, https://github.com/jabaapplets/hibee
Project-URL: Tracker, https://code.hibeeproject.com/
Classifier: Development Status :: 2 - Pre-Alpha
Classifier: Environment :: Web Environment
Classifier: Intended Audience :: Developers
Classifier: License :: OSI Approved :: BSD License
Classifier: Operating System :: OS Independent
Classifier: Programming Language :: Python
Classifier: Programming Language :: Python :: 3
Classifier: Programming Language :: Python :: 3 :: Only
Classifier: Programming Language :: Python :: 3.10
Classifier: Programming Language :: Python :: 3.11
Classifier: Topic :: Internet :: WWW/HTTP
Classifier: Topic :: Internet :: WWW/HTTP :: Dynamic Content
Classifier: Topic :: Internet :: WWW/HTTP :: WSGI
Classifier: Topic :: Software Development :: Libraries :: Application Frameworks
Classifier: Topic :: Software Development :: Libraries :: Python Modules
Requires-Python: >=3.10
Provides-Extra: argon2
Provides-Extra: bcrypt
License-File: license
License-File: license.python
License-File: authors
